{"cameraMode":{"drawMode":0,"name":"Shaded","section":"Shading Mode"},"sceneLighting":true,"audioPlay":false,"sceneViewState":{"showFog":true,"showMaterialUpdate":false,"showSkybox":true,"showFlares":true,"showImageEffects":true,"showParticleSystems":true},"in2DMode":false,"pivot":{"x":277.15362548828127,"y":228.65045166015626,"z":-135.21043395996095},"rotation":{"x":-0.21583996713161469,"y":-0.3280959129333496,"z":0.0772758424282074,"w":-0.9164195656776428},"size":888.9058227539063,"orthographic":false}